MANIFEST.in
README.md
setup.py
docs/api.rst
docs/conf.py
docs/config.rst
docs/extractor.rst
docs/index.rst
docs/install.rst
docs/process.rst
docs/testing.rst
ftr/__init__.py
ftr/config.py
ftr/extractor.py
ftr/process.py
ftr/version.py
ftr.egg-info/PKG-INFO
ftr.egg-info/SOURCES.txt
ftr.egg-info/dependency_links.txt
ftr.egg-info/requires.txt
ftr.egg-info/top_level.txt
ftr/app/__init__.py