Metadata-Version: 1.1
Name: ftr
Version: 0.9.3
Summary: HTML Article cleaner / extractor, Five-Filters compatible.
Home-page: https://github.com/1flow/python-ftr
Author: Olivier Cortès
Author-email: contact@oliviercortes.com
License: AGPLv3
Keywords: parsing,websites,articles
Platform: UNKNOWN
Classifier: Programming Language :: Python
Classifier: Development Status :: 5 - Production/Stable
Classifier: License :: OSI Approved :: GNU Affero General Public License v3 or later (AGPLv3+)
Classifier: Natural Language :: English
Classifier: Operating System :: OS Independent
Classifier: Programming Language :: Python :: 2.7
Classifier: Topic :: Text Processing :: Filters
